{
  "brand": "Apple",
  "layer": "sales",
  "period": "2023-Q3",
  "data": [
    {
      "date": "2023-07-05",
      "sku": "iPhone 14",
      "units_sold": 20000,
      "revenue_inr": 260000000,
      "channel": "Online",
      "refunds": 300,
      "new_customers": 8000
    },
    {
      "date": "2023-07-10",
      "sku": "MacBook Air M2",
      "units_sold": 10000,
      "revenue_inr": 130000000,
      "channel": "Retail",
      "refunds": 150,
      "new_customers": 4000
    },
    {
      "date": "2023-07-20",
      "sku": "iOS 16",
      "units_sold": 15000,
      "revenue_inr": 15000000,
      "channel": "App Store",
      "refunds": 200,
      "new_customers": 6000
    },
    {
      "date": "2023-08-01",
      "sku": "iPhone 14",
      "units_sold": 18000,
      "revenue_inr": 234000000,
      "channel": "Retail",
      "refunds": 250,
      "new_customers": 7500
    },
    {
      "date": "2023-08-15",
      "sku": "AirPods Pro",
      "units_sold": 22000,
      "revenue_inr": 39600000,
      "channel": "Online",
      "refunds": 130,
      "new_customers": 9000
    },
    {
      "date": "2023-08-25",
      "sku": "Apple Security Plan",
      "units_sold": 5000,
      "revenue_inr": 5000000,
      "channel": "Online",
      "refunds": 100,
      "new_customers": 2000
    },
    {
      "date": "2023-09-05",
      "sku": "Apple Pay",
      "units_sold": 3000,
      "revenue_inr": 9000000,
      "channel": "Digital",
      "refunds": 80,
      "new_customers": 1000
    },
    {
      "date": "2023-09-20",
      "sku": "Sustainability Plan",
      "units_sold": 7000,
      "revenue_inr": 3500000,
      "channel": "Retail",
      "refunds": 60,
      "new_customers": 1500
    }
  ]
}